[
 {"name":"dcl_zssys_web_ply_vhlowner","up":[{"s_col":"busi_date","t_tab":"dcl_zssys_web_ply_vhlowner","s_tab":"zssys_web_ply_vhlowner","t_col":"busi_date","type":"node"},{"s_col":"c_app_no","t_tab":"dcl_zssys_web_ply_vhlowner","s_tab":"zssys_web_ply_vhlowner","t_col":"c_app_no","type":"node"},{"s_col":"c_certf_cde","t_tab":"dcl_zssys_web_ply_vhlowner","s_tab":"zssys_web_ply_vhlowner","t_col":"c_certf_cde","type":"node"},{"s_col":"c_certf_cls","t_tab":"dcl_zssys_web_ply_vhlowner","s_tab":"zssys_web_ply_vhlowner","t_col":"c_certf_cls","type":"node"},{"s_col":"c_clnt_addr","t_tab":"dcl_zssys_web_ply_vhlowner","s_tab":"zssys_web_ply_vhlowner","t_col":"c_clnt_addr","type":"node"},{"s_col":"c_crt_cde","t_tab":"dcl_zssys_web_ply_vhlowner","s_tab":"zssys_web_ply_vhlowner","t_col":"c_crt_cde","type":"node"},{"s_col":"c_edr_no","t_tab":"dcl_zssys_web_ply_vhlowner","s_tab":"zssys_web_ply_vhlowner","t_col":"c_edr_no","type":"node"},{"s_col":"c_latest_mrk","t_tab":"dcl_zssys_web_ply_vhlowner","s_tab":"zssys_web_ply_vhlowner","t_col":"c_latest_mrk","type":"node"},{"s_col":"c_mobile","t_tab":"dcl_zssys_web_ply_vhlowner","s_tab":"zssys_web_ply_vhlowner","t_col":"c_mobile","type":"node"},{"s_col":"c_owner_cde","t_tab":"dcl_zssys_web_ply_vhlowner","s_tab":"zssys_web_ply_vhlowner","t_col":"c_owner_cde","type":"node"},{"s_col":"c_owner_cls","t_tab":"dcl_zssys_web_ply_vhlowner","s_tab":"zssys_web_ply_vhlowner","t_col":"c_owner_cls","type":"node"},{"s_col":"c_owner_nme","t_tab":"dcl_zssys_web_ply_vhlowner","s_tab":"zssys_web_ply_vhlowner","t_col":"c_owner_nme","type":"node"},{"s_col":"c_ply_no","t_tab":"dcl_zssys_web_ply_vhlowner","s_tab":"zssys_web_ply_vhlowner","t_col":"c_ply_no","type":"node"},{"s_col":"c_resid_addr","t_tab":"dcl_zssys_web_ply_vhlowner","s_tab":"zssys_web_ply_vhlowner","t_col":"c_resid_addr","type":"node"},{"s_col":"c_resv_txt_1","t_tab":"dcl_zssys_web_ply_vhlowner","s_tab":"zssys_web_ply_vhlowner","t_col":"c_resv_txt_1","type":"node"},{"s_col":"c_resv_txt_2","t_tab":"dcl_zssys_web_ply_vhlowner","s_tab":"zssys_web_ply_vhlowner","t_col":"c_resv_txt_2","type":"node"},{"s_col":"c_resv_txt_3","t_tab":"dcl_zssys_web_ply_vhlowner","s_tab":"zssys_web_ply_vhlowner","t_col":"c_resv_txt_3","type":"node"},{"s_col":"c_sex","t_tab":"dcl_zssys_web_ply_vhlowner","s_tab":"zssys_web_ply_vhlowner","t_col":"c_sex","type":"node"},{"s_col":"c_trans_mrk","t_tab":"dcl_zssys_web_ply_vhlowner","s_tab":"zssys_web_ply_vhlowner","t_col":"c_trans_mrk","type":"node"},{"s_col":"c_upd_cde","t_tab":"dcl_zssys_web_ply_vhlowner","s_tab":"zssys_web_ply_vhlowner","t_col":"c_upd_cde","type":"node"},{"s_col":"c_workdpt_kind","t_tab":"dcl_zssys_web_ply_vhlowner","s_tab":"zssys_web_ply_vhlowner","t_col":"c_workdpt_kind","type":"node"},{"s_col":"c_zip_cde","t_tab":"dcl_zssys_web_ply_vhlowner","s_tab":"zssys_web_ply_vhlowner","t_col":"c_zip_cde","type":"node"},{"s_col":"n_edr_prj_no","t_tab":"dcl_zssys_web_ply_vhlowner","s_tab":"zssys_web_ply_vhlowner","t_col":"n_edr_prj_no","type":"node"},{"s_col":"t_birthday","t_tab":"dcl_zssys_web_ply_vhlowner","s_tab":"zssys_web_ply_vhlowner","t_col":"t_birthday","type":"node"},{"s_col":"t_crt_tm","t_tab":"dcl_zssys_web_ply_vhlowner","s_tab":"zssys_web_ply_vhlowner","t_col":"t_crt_tm","type":"node"},{"s_col":"t_trans_tm","t_tab":"dcl_zssys_web_ply_vhlowner","s_tab":"zssys_web_ply_vhlowner","t_col":"t_trans_tm","type":"node"},{"s_col":"t_upd_tm","t_tab":"dcl_zssys_web_ply_vhlowner","s_tab":"zssys_web_ply_vhlowner","t_col":"t_upd_tm","type":"node"}],"down":[{"s_col":"c_app_no","t_tab":"dw_zssys_web_ply_vhlowner_noact","s_tab":"dcl_zssys_web_ply_vhlowner","t_col":"application_no","type":"node"},{"s_col":"c_app_no","t_tab":"dw_zssys_web_ply_vhlowner_act","s_tab":"dcl_zssys_web_ply_vhlowner","t_col":"application_no","type":"node"},{"s_col":"certf_no","t_tab":"tmp_zygs_before_vhlown","s_tab":"dw_zssys_web_ply_vhlowner_act","t_col":"certfno","type":"node"},{"s_col":"certf_no","t_tab":"tmp_zygs_before_vhlown","s_tab":"dw_zssys_web_ply_vhlowner_act","t_col":"clientoneid","type":"node"},{"s_col":"certf_no","t_tab":"mdp_claim_main","s_tab":"dw_zssys_web_ply_vhlowner_act","t_col":"certf_no","type":"node"},{"s_col":"certf_no","t_tab":"mdp_vas_relationship","s_tab":"dw_zssys_web_ply_vhlowner_act","t_col":"vhl_owner_certf_no","type":"node"},{"s_col":"c_certf_cde","t_tab":"dw_zssys_web_ply_vhlowner_act","s_tab":"dcl_zssys_web_ply_vhlowner","t_col":"certf_no","type":"node"},{"s_col":"c_certf_cde","t_tab":"dw_zssys_web_ply_vhlowner_noact","s_tab":"dcl_zssys_web_ply_vhlowner","t_col":"certf_no","type":"node"},{"s_col":"c_certf_cls","t_tab":"dw_zssys_web_ply_vhlowner_act","s_tab":"dcl_zssys_web_ply_vhlowner","t_col":"certf_type","type":"node"},{"s_col":"c_certf_cls","t_tab":"dw_zssys_web_ply_vhlowner_noact","s_tab":"dcl_zssys_web_ply_vhlowner","t_col":"certf_type","type":"node"},{"s_col":"c_clnt_addr","t_tab":"dw_zssys_web_ply_vhlowner_act","s_tab":"dcl_zssys_web_ply_vhlowner","t_col":"addr","type":"node"},{"s_col":"c_clnt_addr","t_tab":"dw_zssys_web_ply_vhlowner_noact","s_tab":"dcl_zssys_web_ply_vhlowner","t_col":"addr","type":"node"},{"s_col":"c_crt_cde","t_tab":"dw_zssys_web_ply_vhlowner_act","s_tab":"dcl_zssys_web_ply_vhlowner","t_col":"crt_cde","type":"node"},{"s_col":"c_crt_cde","t_tab":"dw_zssys_web_ply_vhlowner_noact","s_tab":"dcl_zssys_web_ply_vhlowner","t_col":"crt_cde","type":"node"},{"s_col":"c_edr_no","t_tab":"dw_zssys_web_ply_vhlowner_act","s_tab":"dcl_zssys_web_ply_vhlowner","t_col":"edr_no","type":"node"},{"s_col":"c_edr_no","t_tab":"dw_zssys_web_ply_vhlowner_noact","s_tab":"dcl_zssys_web_ply_vhlowner","t_col":"edr_no","type":"node"},{"s_col":"c_mobile","t_tab":"dw_zssys_web_ply_vhlowner_noact","s_tab":"dcl_zssys_web_ply_vhlowner","t_col":"vhl_owner_mobile","type":"node"},{"s_col":"vhl_owner_mobile","t_tab":"mdp_vas_relationship","s_tab":"dw_zssys_web_ply_vhlowner_act","t_col":"vhl_owner_mobile","type":"node"},{"s_col":"c_mobile","t_tab":"dw_zssys_web_ply_vhlowner_act","s_tab":"dcl_zssys_web_ply_vhlowner","t_col":"vhl_owner_mobile","type":"node"},{"s_col":"c_owner_cde","t_tab":"dw_zssys_web_ply_vhlowner_noact","s_tab":"dcl_zssys_web_ply_vhlowner","t_col":"vhl_owner_cde","type":"node"},{"s_col":"c_owner_cde","t_tab":"dw_zssys_web_ply_vhlowner_act","s_tab":"dcl_zssys_web_ply_vhlowner","t_col":"vhl_owner_cde","type":"node"},{"s_col":"c_owner_cls","t_tab":"dw_zssys_web_ply_vhlowner_noact","s_tab":"dcl_zssys_web_ply_vhlowner","t_col":"vhl_owner_type","type":"node"},{"s_col":"c_owner_cls","t_tab":"dw_zssys_web_ply_vhlowner_act","s_tab":"dcl_zssys_web_ply_vhlowner","t_col":"vhl_owner_type","type":"node"},{"s_col":"c_owner_nme","t_tab":"dw_zssys_web_ply_vhlowner_noact","s_tab":"dcl_zssys_web_ply_vhlowner","t_col":"vhl_owner_nme","type":"node"},{"s_col":"vhl_owner_nme","t_tab":"mdp_claim_main","s_tab":"dw_zssys_web_ply_vhlowner_act","t_col":"vhl_owner_nme","type":"node"},{"s_col":"vhl_owner_nme","t_tab":"mdp_vas_relationship","s_tab":"dw_zssys_web_ply_vhlowner_act","t_col":"vhl_owner_nme","type":"node"},{"s_col":"c_owner_nme","t_tab":"dw_zssys_web_ply_vhlowner_act","s_tab":"dcl_zssys_web_ply_vhlowner","t_col":"vhl_owner_nme","type":"node"},{"s_col":"c_ply_no","t_tab":"dw_zssys_web_ply_vhlowner_noact","s_tab":"dcl_zssys_web_ply_vhlowner","t_col":"policy_no","type":"node"},{"s_col":"c_ply_no","t_tab":"dw_zssys_web_ply_vhlowner_act","s_tab":"dcl_zssys_web_ply_vhlowner","t_col":"policy_no","type":"node"},{"s_col":"c_upd_cde","t_tab":"dw_zssys_web_ply_vhlowner_noact","s_tab":"dcl_zssys_web_ply_vhlowner","t_col":"upd_cde","type":"node"},{"s_col":"c_upd_cde","t_tab":"dw_zssys_web_ply_vhlowner_act","s_tab":"dcl_zssys_web_ply_vhlowner","t_col":"upd_cde","type":"node"},{"s_col":"c_zip_cde","t_tab":"dw_zssys_web_ply_vhlowner_act","s_tab":"dcl_zssys_web_ply_vhlowner","t_col":"postcode","type":"node"},{"s_col":"c_zip_cde","t_tab":"dw_zssys_web_ply_vhlowner_noact","s_tab":"dcl_zssys_web_ply_vhlowner","t_col":"postcode","type":"node"},{"s_col":"t_crt_tm","t_tab":"dw_zssys_web_ply_vhlowner_noact","s_tab":"dcl_zssys_web_ply_vhlowner","t_col":"crt_date","type":"node"},{"s_col":"t_crt_tm","t_tab":"dw_zssys_web_ply_vhlowner_act","s_tab":"dcl_zssys_web_ply_vhlowner","t_col":"crt_date","type":"node"},{"s_col":"t_upd_tm","t_tab":"dw_zssys_web_ply_vhlowner_noact","s_tab":"dcl_zssys_web_ply_vhlowner","t_col":"upd_date","type":"node"},{"s_col":"t_upd_tm","t_tab":"dw_zssys_web_ply_vhlowner_act","s_tab":"dcl_zssys_web_ply_vhlowner","t_col":"upd_date","type":"node"}]}
,{"name":"dw_zssys_web_ply_vhlowner_act","up":[{"s_col":"c_clnt_addr","t_tab":"dcl_zssys_web_ply_vhlowner","s_tab":"zssys_web_ply_vhlowner","t_col":"c_clnt_addr","type":"node"},{"s_col":"c_clnt_addr","t_tab":"dw_zssys_web_ply_vhlowner_act","s_tab":"dcl_zssys_web_ply_vhlowner","t_col":"addr","type":"node"},{"s_col":"c_app_no","t_tab":"dcl_zssys_web_ply_vhlowner","s_tab":"zssys_web_ply_vhlowner","t_col":"c_app_no","type":"node"},{"s_col":"c_app_no","t_tab":"dw_zssys_web_ply_vhlowner_act","s_tab":"dcl_zssys_web_ply_vhlowner","t_col":"application_no","type":"node"},{"s_col":"c_certf_c","t_tab":"dw_zssys_web_ply_vhlowner_act","s_tab":"dcl_zssys_web_ply_vhlowner","t_col":"birthday","type":"node"},{"s_col":"c_certf_cde","t_tab":"dcl_zssys_web_ply_vhlowner","s_tab":"zssys_web_ply_vhlowner","t_col":"c_certf_cde","type":"node"},{"s_col":"c_certf_cde","t_tab":"dw_zssys_web_ply_vhlowner_act","s_tab":"dcl_zssys_web_ply_vhlowner","t_col":"certf_no","type":"node"},{"s_col":"c_certf_cls","t_tab":"dcl_zssys_web_ply_vhlowner","s_tab":"zssys_web_ply_vhlowner","t_col":"c_certf_cls","type":"node"},{"s_col":"c_certf_cls","t_tab":"dw_zssys_web_ply_vhlowner_act","s_tab":"dcl_zssys_web_ply_vhlowner","t_col":"certf_type","type":"node"},{"s_col":"c_crt_cde","t_tab":"dcl_zssys_web_ply_vhlowner","s_tab":"zssys_web_ply_vhlowner","t_col":"c_crt_cde","type":"node"},{"s_col":"c_crt_cde","t_tab":"dw_zssys_web_ply_vhlowner_act","s_tab":"dcl_zssys_web_ply_vhlowner","t_col":"crt_cde","type":"node"},{"s_col":"t_crt_tm","t_tab":"dcl_zssys_web_ply_vhlowner","s_tab":"zssys_web_ply_vhlowner","t_col":"t_crt_tm","type":"node"},{"s_col":"t_crt_tm","t_tab":"dw_zssys_web_ply_vhlowner_act","s_tab":"dcl_zssys_web_ply_vhlowner","t_col":"crt_date","type":"node"},{"s_col":"c_edr_no","t_tab":"dcl_zssys_web_ply_vhlowner","s_tab":"zssys_web_ply_vhlowner","t_col":"c_edr_no","type":"node"},{"s_col":"c_edr_no","t_tab":"dw_zssys_web_ply_vhlowner_act","s_tab":"dcl_zssys_web_ply_vhlowner","t_col":"edr_no","type":"node"},{"s_col":"c_ply_no","t_tab":"dcl_zssys_web_ply_vhlowner","s_tab":"zssys_web_ply_vhlowner","t_col":"c_ply_no","type":"node"},{"s_col":"c_ply_no","t_tab":"dw_zssys_web_ply_vhlowner_act","s_tab":"dcl_zssys_web_ply_vhlowner","t_col":"policy_no","type":"node"},{"s_col":"c_zip_cde","t_tab":"dcl_zssys_web_ply_vhlowner","s_tab":"zssys_web_ply_vhlowner","t_col":"c_zip_cde","type":"node"},{"s_col":"c_zip_cde","t_tab":"dw_zssys_web_ply_vhlowner_act","s_tab":"dcl_zssys_web_ply_vhlowner","t_col":"postcode","type":"node"},{"s_col":"c_s","t_tab":"dw_zssys_web_ply_vhlowner_act","s_tab":"dcl_zssys_web_ply_vhlowner","t_col":"sex","type":"node"},{"s_col":"c_upd_cde","t_tab":"dcl_zssys_web_ply_vhlowner","s_tab":"zssys_web_ply_vhlowner","t_col":"c_upd_cde","type":"node"},{"s_col":"c_upd_cde","t_tab":"dw_zssys_web_ply_vhlowner_act","s_tab":"dcl_zssys_web_ply_vhlowner","t_col":"upd_cde","type":"node"},{"s_col":"t_upd_tm","t_tab":"dcl_zssys_web_ply_vhlowner","s_tab":"zssys_web_ply_vhlowner","t_col":"t_upd_tm","type":"node"},{"s_col":"t_upd_tm","t_tab":"dw_zssys_web_ply_vhlowner_act","s_tab":"dcl_zssys_web_ply_vhlowner","t_col":"upd_date","type":"node"},{"s_col":"c_owner_cde","t_tab":"dcl_zssys_web_ply_vhlowner","s_tab":"zssys_web_ply_vhlowner","t_col":"c_owner_cde","type":"node"},{"s_col":"c_owner_cde","t_tab":"dw_zssys_web_ply_vhlowner_act","s_tab":"dcl_zssys_web_ply_vhlowner","t_col":"vhl_owner_cde","type":"node"},{"s_col":"c_mobile","t_tab":"dcl_zssys_web_ply_vhlowner","s_tab":"zssys_web_ply_vhlowner","t_col":"c_mobile","type":"node"},{"s_col":"c_mobile","t_tab":"dw_zssys_web_ply_vhlowner_act","s_tab":"dcl_zssys_web_ply_vhlowner","t_col":"vhl_owner_mobile","type":"node"},{"s_col":"c_biz_mrk","t_tab":"dcl_zssys_web_ply_vhl","s_tab":"zssys_web_ply_vhl","t_col":"c_biz_mrk","type":"node"},{"s_col":"c_biz_mrk","t_tab":"dw_zssys_web_ply_vhlowner_act","s_tab":"dcl_zssys_web_ply_vhl","t_col":"vhl_owner_nature_cde","type":"node"},{"s_col":"c_owner_nme","t_tab":"dcl_zssys_web_ply_vhlowner","s_tab":"zssys_web_ply_vhlowner","t_col":"c_owner_nme","type":"node"},{"s_col":"c_owner_nme","t_tab":"dw_zssys_web_ply_vhlowner_act","s_tab":"dcl_zssys_web_ply_vhlowner","t_col":"vhl_owner_nme","type":"node"},{"s_col":"c_owner_cls","t_tab":"dcl_zssys_web_ply_vhlowner","s_tab":"zssys_web_ply_vhlowner","t_col":"c_owner_cls","type":"node"},{"s_col":"c_owner_cls","t_tab":"dw_zssys_web_ply_vhlowner_act","s_tab":"dcl_zssys_web_ply_vhlowner","t_col":"vhl_owner_type","type":"node"},{"s_col":"c_workdpt_ki","t_tab":"dw_zssys_web_ply_vhlowner_act","s_tab":"dcl_zssys_web_ply_vhlowner","t_col":"workplace_nature","type":"node"}],"down":[{"s_col":"certf_no","t_tab":"tmp_zygs_before_vhlown","s_tab":"dw_zssys_web_ply_vhlowner_act","t_col":"certfno","type":"node"},{"s_col":"certf_no","t_tab":"tmp_zygs_before_vhlown","s_tab":"dw_zssys_web_ply_vhlowner_act","t_col":"clientoneid","type":"node"},{"s_col":"certf_no","t_tab":"mdp_claim_main","s_tab":"dw_zssys_web_ply_vhlowner_act","t_col":"certf_no","type":"node"},{"s_col":"certf_no","t_tab":"mdp_vas_relationship","s_tab":"dw_zssys_web_ply_vhlowner_act","t_col":"vhl_owner_certf_no","type":"node"},{"s_col":"vhl_owner_mobile","t_tab":"mdp_vas_relationship","s_tab":"dw_zssys_web_ply_vhlowner_act","t_col":"vhl_owner_mobile","type":"node"},{"s_col":"vhl_owner_nme","t_tab":"mdp_claim_main","s_tab":"dw_zssys_web_ply_vhlowner_act","t_col":"vhl_owner_nme","type":"node"},{"s_col":"vhl_owner_nme","t_tab":"mdp_vas_relationship","s_tab":"dw_zssys_web_ply_vhlowner_act","t_col":"vhl_owner_nme","type":"node"},{"s_col":"application_no","t_tab":"mdp_zssys_web_ply_vhlowner","s_tab":"dw_zssys_web_ply_vhlowner_act","t_col":"app_num","type":"node"},{"s_col":"application_no","t_tab":"mdp_zssys_web_bonhams","s_tab":"dw_zssys_web_ply_vhlowner_act","t_col":"gold","type":"node"},{"s_col":"application_no","t_tab":"mdp_jewels","s_tab":"dw_zssys_web_ply_vhlowner_act","t_col":"biridge","type":"node"}]}
,{"name":"mdp_zssys_web_bonhams","down":[{"s_col":"gold","t_tab":"mdp_zssys_web_london","s_tab":"mdp_zssys_web_bonhams","t_col":"auction","type":"node"},{"s_col":"gold","t_tab":"mdp_adv_knights","s_tab":"mdp_zssys_web_bonhams","t_col":"bonhams_knights","type":"node"}]}
,{"name":"abc","up":[{"s_col":"abc_1","t_tab":"abc","s_tab":"ods_abc","t_col":"ods_1"},{"s_col":"abc_2","t_tab":"abc","s_tab":"ods_abc","t_col":"ods_2"},{"s_col":"abc_3","t_tab":"abc","s_tab":"ods_abc","t_col":"ods_3"},{"s_col":"abc_4","t_tab":"abc","s_tab":"ods_abc","t_col":"ods_4"},{"s_col":"abc_1","t_tab":"abc","s_tab":"ods_edf","t_col":"ods_1"},{"s_col":"abc_2","t_tab":"abc","s_tab":"ods_edf","t_col":"ods_2"}],"down":[]}
,{"name":"ods_abc","up":[{"s_col":"abc_1","t_tab":"ods_abc","s_tab":"ods_eff","t_col":"ods_1"},{"s_col":"abc_2","t_tab":"ods_abc","s_tab":"ods_eff","t_col":"ods_2"}],"down":[]}
,{"name":"ods_edf","up":[{"s_col":"ods_1","t_tab":"ods_edf","s_tab":"ods_vnndf","t_col":"abc_1"},{"s_col":"abc_2","t_tab":"ods_edf","s_tab":"ods_vnndf","t_col":"ods_2"}],"down":[]}
,{"name":"ods_vnndf","up":[{"s_col":"vnndf_cert","t_tab":"ods_vnndf","s_tab":"zssys_vnndf","t_col":"ods_1"},{"s_col":"abc_2","t_tab":"ods_vnndf","s_tab":"zssys_web_vnndf","t_col":"ods_1"}],"down":[]}
]