{
    "name":"mdp_channel_prpssalary",
    "up":[
        {
            "s_col":"md_sub_cde",
            "t_tab":"dim_i_sc",
            "s_tab":"ods_zssy",
            "t_col":"md_sub_cde",
            "type":"node"
        },
        {
            "s_col":"md_sub_cde",
            "t_tab":"dw_sales_prpssalary",
            "s_tab":"dim_i_sc",
            "t_col":"sale_payment_way",
            "type":"node"
        },
        {
            "s_col":"sale_payment_way",
            "t_tab":"mdp_channel_prpssalary",
            "s_tab":"dw_sales_prpssalary",
            "t_col":"sale_payment_way_cnm",
            "type":"node"
        }
    ],
    "down":[
        {
            "s_col":"sale_payment_way_cnm",
            "t_tab":"dw_prpssalary",
            "s_tab":"mdp_channel_prpssalary",
            "t_col":"way_cnm",
            "type":"node"
        },
        {
            "s_col":"way_cnm",
            "t_tab":"mdp_cusdm_vhlhumaninjury_detail",
            "s_tab":"dw_prpssalary",
            "t_col":"hi_loss_type",
            "type":"node"
        }
    ]
}